deepaste/__init__.py
deepaste/deepaste.py
deepaste-1.0.2.dist-info/entry_points.txt
deepaste-1.0.2.dist-info/LICENSE
deepaste-1.0.2.dist-info/WHEEL
deepaste-1.0.2.dist-info/METADATA
deepaste-1.0.2.dist-info/RECORD
